{
    "silver_fiyatlari": [
        {
            "tarih": "2024-12-23",
            "fiyat": 28.84
        },
        {
            "tarih": "2024-12-22",
            "fiyat": 28.85
        },
        {
            "tarih": "2024-12-21",
            "fiyat": 25.53
        },
        {
            "tarih": "2024-12-20",
            "fiyat": 20.61
        },
        {
            "tarih": "2024-12-19",
            "fiyat": 21.12
        },
        {
            "tarih": "2024-12-18",
            "fiyat": 20.23
        },
        {
            "tarih": "2024-12-17",
            "fiyat": 25.54
        }
    ]
}